{"v":"4.10.2","fr":29.9700012207031,"ip":0,"op":63.0000025660426,"w":1920,"h":1080,"nm":"コンポ 1","ddd":0,"assets":[],"layers":[{"ddd":0,"ind":1,"ty":9,"nm":"MLG Green Screen - Click nice.mp4","cl":"mp4","sr":1,"ks":{"o":{"a":0,"k":100,"ix":11},"r":{"a":0,"k":0,"ix":10},"p":{"a":0,"k":[960,540,0],"ix":2},"a":{"a":0,"k":[640,360,0],"ix":1},"s":{"a":0,"k":[100,100,100],"ix":6}},"ao":0,"ef":[{"ty":5,"nm":"Keylight (1.2)","np":81,"mn":"Keylight 906","ix":1,"en":1,"ef":[{"ty":6,"nm":"About","mn":"Keylight 906-0001","ix":1,"v":0},{"ty":7,"nm":"View","mn":"Keylight 906-0002","ix":2,"v":{"a":0,"k":11,"ix":2}},{"ty":7,"nm":"Unpremultiply Result","mn":"Keylight 906-0003","ix":3,"v":{"a":0,"k":1,"ix":3}},{"ty":2,"nm":"Screen Colour","mn":"Keylight 906-0004","ix":4,"v":{"a":0,"k":[0,1,0,1],"ix":4}},{"ty":0,"nm":"Screen Gain","mn":"Keylight 906-0005","ix":5,"v":{"a":0,"k":100,"ix":5}},{"ty":0,"nm":"Screen Balance","mn":"Keylight 906-0006","ix":6,"v":{"a":0,"k":50,"ix":6}},{"ty":2,"nm":"Despill Bias","mn":"Keylight 906-0007","ix":7,"v":{"a":0,"k":[0.498039215686,0.498039215686,0.498039215686,1],"ix":7}},{"ty":2,"nm":"Alpha Bias","mn":"Keylight 906-0008","ix":8,"v":{"a":0,"k":[0.498039215686,0.498039215686,0.498039215686,1],"ix":8}},{"ty":7,"nm":"Lock Biases Together","mn":"Keylight 906-0009","ix":9,"v":{"a":0,"k":1,"ix":9}},{"ty":0,"nm":"Screen Pre-blur","mn":"Keylight 906-0010","ix":10,"v":{"a":0,"k":0,"ix":10}},{"ty":6,"nm":"Screen Matte","mn":"Keylight 906-0011","ix":11,"v":0},{"ty":0,"nm":"Clip Black","mn":"Keylight 906-0012","ix":12,"v":{"a":0,"k":0,"ix":12}},{"ty":0,"nm":"Clip White","mn":"Keylight 906-0013","ix":13,"v":{"a":0,"k":100,"ix":13}},{"ty":0,"nm":"Clip Rollback","mn":"Keylight 906-0014","ix":14,"v":{"a":0,"k":0,"ix":14}},{"ty":0,"nm":"Screen Shrink/Grow","mn":"Keylight 906-0015","ix":15,"v":{"a":0,"k":0,"ix":15}},{"ty":0,"nm":"Screen Softness","mn":"Keylight 906-0016","ix":16,"v":{"a":0,"k":0,"ix":16}},{"ty":0,"nm":"Screen Despot Black","mn":"Keylight 906-0017","ix":17,"v":{"a":0,"k":0,"ix":17}},{"ty":0,"nm":"Screen Despot White","mn":"Keylight 906-0018","ix":18,"v":{"a":0,"k":0,"ix":18}},{"ty":7,"nm":"Replace Method","mn":"Keylight 906-0019","ix":19,"v":{"a":0,"k":4,"ix":19}},{"ty":2,"nm":"Replace Colour","mn":"Keylight 906-0020","ix":20,"v":{"a":0,"k":[0.498039215686,0.498039215686,0.498039215686,1],"ix":20}},{"ty":6,"nm":"Screen Matte","mn":"Keylight 906-0021","ix":21,"v":0},{"ty":6,"nm":"Inside Mask","mn":"Keylight 906-0022","ix":22,"v":0},{"ty":10,"nm":"Inside Mask","mn":"Keylight 906-0023","ix":23,"v":{"a":0,"k":0,"ix":23}},{"ty":0,"nm":"Inside Mask Softness","mn":"Keylight 906-0024","ix":24,"v":{"a":0,"k":0,"ix":24}},{"ty":7,"nm":"Invert","mn":"Keylight 906-0025","ix":25,"v":{"a":0,"k":0,"ix":25}},{"ty":7,"nm":"Replace Method","mn":"Keylight 906-0026","ix":26,"v":{"a":0,"k":2,"ix":26}},{"ty":2,"nm":"Replace Colour","mn":"Keylight 906-0027","ix":27,"v":{"a":0,"k":[0.498039215686,0.498039215686,0.498039215686,1],"ix":27}},{"ty":7,"nm":"Source Alpha","mn":"Keylight 906-0028","ix":28,"v":{"a":0,"k":3,"ix":28}},{"ty":6,"nm":"Inside Mask","mn":"Keylight 906-0029","ix":29,"v":0},{"ty":6,"nm":"Outside Mask","mn":"Keylight 906-0030","ix":30,"v":0},{"ty":10,"nm":"Outside Mask","mn":"Keylight 906-0031","ix":31,"v":{"a":0,"k":0,"ix":31}},{"ty":0,"nm":"Outside Mask Softness","mn":"Keylight 906-0032","ix":32,"v":{"a":0,"k":0,"ix":32}},{"ty":7,"nm":"Invert","mn":"Keylight 906-0033","ix":33,"v":{"a":0,"k":0,"ix":33}},{"ty":6,"nm":"Outside Mask","mn":"Keylight 906-0034","ix":34,"v":0},{"ty":6,"nm":"Foreground Colour Correction","mn":"Keylight 906-0035","ix":35,"v":0},{"ty":7,"nm":"Enable Colour Correction","mn":"Keylight 906-0036","ix":36,"v":{"a":0,"k":0,"ix":36}},{"ty":0,"nm":"Saturation","mn":"Keylight 906-0037","ix":37,"v":{"a":0,"k":100,"ix":37}},{"ty":0,"nm":"Contrast","mn":"Keylight 906-0038","ix":38,"v":{"a":0,"k":0,"ix":38}},{"ty":0,"nm":"Brightness","mn":"Keylight 906-0039","ix":39,"v":{"a":0,"k":0,"ix":39}},{"ty":6,"nm":"Colour Suppression","mn":"Keylight 906-0040","ix":40,"v":0},{"ty":7,"nm":"Suppress","mn":"Keylight 906-0041","ix":41,"v":{"a":0,"k":1,"ix":41}},{"ty":0,"nm":"Suppression Balance","mn":"Keylight 906-0042","ix":42,"v":{"a":0,"k":50,"ix":42}},{"ty":0,"nm":"Suppression Amount","mn":"Keylight 906-0043","ix":43,"v":{"a":0,"k":100,"ix":43}},{"ty":6,"nm":"Colour Suppression","mn":"Keylight 906-0044","ix":44,"v":0},{"ty":6,"nm":"Colour Balancing","mn":"Keylight 906-0045","ix":45,"v":0},{"ty":0,"nm":"Hue","mn":"Keylight 906-0046","ix":46,"v":{"a":0,"k":0,"ix":46}},{"ty":0,"nm":"Sat","mn":"Keylight 906-0047","ix":47,"v":{"a":0,"k":0,"ix":47}},{"ty":0,"nm":"Colour Balance Wheel","mn":"Keylight 906-0048","ix":48,"v":{"a":0,"k":0,"ix":48}},{"ty":6,"nm":"Colour Balancing","mn":"Keylight 906-0049","ix":49,"v":0},{"ty":6,"nm":"Foreground Colour Correction","mn":"Keylight 906-0050","ix":50,"v":0},{"ty":6,"nm":"Edge Colour Correction","mn":"Keylight 906-0051","ix":51,"v":0},{"ty":7,"nm":"Enable Edge Colour Correction","mn":"Keylight 906-0052","ix":52,"v":{"a":0,"k":0,"ix":52}},{"ty":0,"nm":"Edge Hardness","mn":"Keylight 906-0053","ix":53,"v":{"a":0,"k":50,"ix":53}},{"ty":0,"nm":"Edge Softness","mn":"Keylight 906-0054","ix":54,"v":{"a":0,"k":0,"ix":54}},{"ty":0,"nm":"Edge Grow","mn":"Keylight 906-0055","ix":55,"v":{"a":0,"k":0,"ix":55}},{"ty":0,"nm":"Saturation","mn":"Keylight 906-0056","ix":56,"v":{"a":0,"k":100,"ix":56}},{"ty":0,"nm":"Contrast","mn":"Keylight 906-0057","ix":57,"v":{"a":0,"k":0,"ix":57}},{"ty":0,"nm":"Brightness","mn":"Keylight 906-0058","ix":58,"v":{"a":0,"k":0,"ix":58}},{"ty":6,"nm":"Edge Colour Suppression","mn":"Keylight 906-0059","ix":59,"v":0},{"ty":7,"nm":"Suppress","mn":"Keylight 906-0060","ix":60,"v":{"a":0,"k":1,"ix":60}},{"ty":0,"nm":"Suppression Balance","mn":"Keylight 906-0061","ix":61,"v":{"a":0,"k":50,"ix":61}},{"ty":0,"nm":"Suppression Amount","mn":"Keylight 906-0062","ix":62,"v":{"a":0,"k":100,"ix":62}},{"ty":6,"nm":"Edge Colour Suppression","mn":"Keylight 906-0063","ix":63,"v":0},{"ty":6,"nm":"Colour Balancing","mn":"Keylight 906-0064","ix":64,"v":0},{"ty":0,"nm":"Hue","mn":"Keylight 906-0065","ix":65,"v":{"a":0,"k":0,"ix":65}},{"ty":0,"nm":"Sat","mn":"Keylight 906-0066","ix":66,"v":{"a":0,"k":0,"ix":66}},{"ty":0,"nm":"Colour Balance Wheel","mn":"Keylight 906-0067","ix":67,"v":{"a":0,"k":0,"ix":67}},{"ty":6,"nm":"Colour Balancing","mn":"Keylight 906-0068","ix":68,"v":0},{"ty":6,"nm":"Edge Colour Correction","mn":"Keylight 906-0069","ix":69,"v":0},{"ty":6,"nm":"Source Crops","mn":"Keylight 906-0070","ix":70,"v":0},{"ty":7,"nm":"X Method","mn":"Keylight 906-0071","ix":71,"v":{"a":0,"k":1,"ix":71}},{"ty":7,"nm":"Y Method","mn":"Keylight 906-0072","ix":72,"v":{"a":0,"k":1,"ix":72}},{"ty":2,"nm":"Edge Colour","mn":"Keylight 906-0073","ix":73,"v":{"a":0,"k":[0,0,0,1],"ix":73}},{"ty":0,"nm":"Edge Colour Alpha","mn":"Keylight 906-0074","ix":74,"v":{"a":0,"k":100,"ix":74}},{"ty":0,"nm":"Left","mn":"Keylight 906-0075","ix":75,"v":{"a":0,"k":0,"ix":75}},{"ty":0,"nm":"Right","mn":"Keylight 906-0076","ix":76,"v":{"a":0,"k":100,"ix":76}},{"ty":0,"nm":"Top","mn":"Keylight 906-0077","ix":77,"v":{"a":0,"k":0,"ix":77}},{"ty":0,"nm":"Bottom","mn":"Keylight 906-0078","ix":78,"v":{"a":0,"k":100,"ix":78}},{"ty":6,"nm":"Source Crops","mn":"Keylight 906-0079","ix":79,"v":0}]}],"ip":0,"op":63.0000025660426,"st":0,"bm":0}]}